{
  "displayName": "TableBody",
  "props": [
    {
      "type": "custom",
      "required": false,
      "description": [
        "An element used to render the Component"
      ],
      "defaultValue": "'tbody'",
      "tags": [],
      "name": "as"
    },
    {
      "type": "node",
      "required": false,
      "description": [
        "Children Props"
      ],
      "tags": [],
      "name": "children"
    },
    {
      "type": "string",
      "required": false,
      "description": [
        "User Defined classes"
      ],
      "tags": [],
      "name": "className"
    },
    {
      "type": "any",
      "required": false,
      "description": [
        "Content shorthand"
      ],
      "tags": [],
      "name": "content"
    }
  ],
  "constructorName": "TableBody",
  "type": "collection",
  "isParent": false,
  "isChild": true,
  "parentDisplayName": "Table",
  "subcomponentName": "Body",
  "subcomponents": null,
  "apiPath": "Table.Body",
  "componentClassName": "body",
  "docblock": {
    "tags": [],
    "description": [
      ""
    ]
  },
  "examplesExist": false,
  "repoPath": "src/react/collections/Table/TableBody.js",
  "filename": "TableBody.js",
  "filenameWithoutExt": "TableBody"
}