{
  "displayName": "TableRow",
  "props": [
    {
      "type": "bool",
      "required": false,
      "description": [
        "Set Row as Active"
      ],
      "tags": [],
      "name": "active"
    },
    {
      "type": "custom",
      "required": false,
      "description": [
        "An element used to render the content"
      ],
      "defaultValue": "'tr'",
      "tags": [],
      "name": "as"
    },
    {
      "type": "custom",
      "required": false,
      "description": [
        "Set the element used to Render the Cells"
      ],
      "defaultValue": "'td'",
      "tags": [],
      "name": "cellAs"
    },
    {
      "type": "arrayOf",
      "required": false,
      "description": [
        "Array of string used to render the cells"
      ],
      "tags": [],
      "value": {
        "name": "any"
      },
      "name": "cells"
    },
    {
      "type": "node",
      "required": false,
      "description": [
        "Children props"
      ],
      "tags": [],
      "name": "children"
    },
    {
      "type": "string",
      "required": false,
      "description": [
        "User defined Classes"
      ],
      "tags": [],
      "name": "className"
    },
    {
      "type": "bool",
      "required": false,
      "description": [
        "Set Row as Disabled"
      ],
      "tags": [],
      "name": "disabled"
    },
    {
      "type": "bool",
      "required": false,
      "description": [
        "Set Row as Error"
      ],
      "tags": [],
      "name": "error"
    },
    {
      "type": "bool",
      "required": false,
      "description": [
        "Set a Row as Selectable"
      ],
      "tags": [],
      "name": "selectable"
    },
    {
      "type": "bool",
      "required": false,
      "description": [
        "Set Row as Success"
      ],
      "tags": [],
      "name": "success"
    },
    {
      "type": "bool",
      "required": false,
      "description": [
        "Set Row as Warning"
      ],
      "tags": [],
      "name": "warning"
    }
  ],
  "constructorName": "TableRow",
  "type": "collection",
  "isParent": false,
  "isChild": true,
  "parentDisplayName": "Table",
  "subcomponentName": "Row",
  "subcomponents": null,
  "apiPath": "Table.Row",
  "componentClassName": "row",
  "docblock": {
    "tags": [],
    "description": [
      ""
    ]
  },
  "examplesExist": false,
  "repoPath": "src/react/collections/Table/TableRow.js",
  "filename": "TableRow.js",
  "filenameWithoutExt": "TableRow"
}